<!--
/**
* Product Menu
*
* @category  Mtwoe
* @package   Mtwoe\ProductMenu
* @author    Andrii Tomkiv <tomkivandrii18@gmail.com>
* @copyright 2023 tomk1v
*/
-->

<form xmlns:xsi="http://www.w3.org/2001/XMLSchema-instance"
      xsi:noNamespaceSchemaLocation="urn:magento:module:Magento_Ui:etc/ui_configuration.xsd">
    <argument name="data" xsi:type="array">
        <item name="js_config" xsi:type="array">
            <item name="provider" xsi:type="string">productmenu_user_form.mtwoe_product_menu_data_source</item>
            <item name="deps" xsi:type="string">productmenu_user_form.mtwoe_product_menu_data_source</item>
        </item>
        <item name="label" xsi:type="string" translate="true">Edit Product Tab</item>
        <item name="config" xsi:type="array">
            <item name="dataScope" xsi:type="string">data</item>
            <item name="namespace" xsi:type="string">mtwoe_productmenu_user_form</item>
        </item>
        <item name="template" xsi:type="string">templates/form/collapsible</item>
        <item name="buttons" xsi:type="array">
            <item name="save" xsi:type="array">
                <item name="name" xsi:type="string">save</item>
                <item name="label" xsi:type="string" translate="true">Save</item>
                <item name="class" xsi:type="string">primary</item>
            </item>
        </item>
    </argument>

    <dataSource name="mtwoe_product_menu_data_source">
        <argument name="data" xsi:type="array">
            <item name="js_config" xsi:type="array">
                <item name="component" xsi:type="string">Magento_Ui/js/form/provider</item>
                <item name="submit_url" path="productmenu/index/saveuser" xsi:type="url" />
            </item>
        </argument>
        <dataProvider class="\Mtwoe\ProductMenu\Ui\DataProvider\ProductMenu\ProductDataProvider"
                      name="mtwoe_product_menu_data_source">
            <settings>
                <requestFieldName>entity_id</requestFieldName>
                <primaryFieldName>entity_id</primaryFieldName>
            </settings>
        </dataProvider>
    </dataSource>

    <fieldset name="general">
        <argument name="data" xsi:type="array">
            <item name="config" xsi:type="array">
                <item name="collapsible" xsi:type="boolean">false</item>
                <item name="label" xsi:type="string" translate="true">User Information</item>
            </item>
        </argument>
        <field name="name">
            <argument name="data" xsi:type="array">
                <item name="config" xsi:type="array">
                    <item name="label" xsi:type="string" translate="true">Name</item>
                    <item name="dataType" xsi:type="string">text</item>
                    <item name="formElement" xsi:type="string">input</item>
                    <item name="dataScope" xsi:type="string">name</item>
                    <item name="validation" xsi:type="array">
                        <item name="required-entry" xsi:type="boolean">true</item>
                    </item>
                </item>
            </argument>
        </field>
        <field name="email">
            <argument name="data" xsi:type="array">
                <item name="config" xsi:type="array">
                    <item name="label" xsi:type="string" translate="true">Email</item>
                    <item name="dataType" xsi:type="string">text</item>
                    <item name="formElement" xsi:type="string">textarea</item>
                    <item name="dataScope" xsi:type="string">email</item>
                    <item name="validation" xsi:type="array">
                        <item name="required-entry" xsi:type="boolean">true</item>
                    </item>
                </item>
            </argument>
        </field>
        <field name="phone">
            <argument name="data" xsi:type="array">
                <item name="config" xsi:type="array">
                    <item name="label" xsi:type="string" translate="true">Phone</item>
                    <item name="dataType" xsi:type="string">text</item>
                    <item name="formElement" xsi:type="string">textarea</item>
                    <item name="dataScope" xsi:type="string">phone</item>
                    <item name="validation" xsi:type="array">
                        <item name="required-entry" xsi:type="boolean">true</item>
                    </item>
                </item>
            </argument>
        </field>
    </fieldset>
</form>
